ldk_lnprototest/__init__.py
ldk_lnprototest/ldk_runner.py
ldk_lnprototest-1.0.1.dist-info/METADATA
ldk_lnprototest-1.0.1.dist-info/WHEEL
ldk_lnprototest-1.0.1.dist-info/RECORD
