Metadata-Version: 2.3
Name: ldk-lnprototest
Version: 1.0.1
Summary: Ldk-Sample Runner for Lnprototest
Author: Prakhar Saxena
Author-email: prakharrsaxena@gmail.com
Requires-Python: >=3.8,<4.0
Classifier: Programming Language :: Python :: 3
Classifier: Programming Language :: Python :: 3.8
Classifier: Programming Language :: Python :: 3.9
Classifier: Programming Language :: Python :: 3.10
Classifier: Programming Language :: Python :: 3.11
Classifier: Programming Language :: Python :: 3.12
Classifier: Programming Language :: Python :: 3.13
Requires-Dist: crc32c (>=2.2.post0,<3.0)
Requires-Dist: pyln-bolt1 (>=1.0.222,<2.0.0)
Requires-Dist: pyln-bolt2 (>=1.0.222,<2.0.0)
Requires-Dist: pyln-bolt4 (>=1.0.222,<2.0.0)
Requires-Dist: pyln-bolt7 (>=1.0.246,<2.0.0)
Requires-Dist: pyln-client (>=0.12.0,<0.13.0)
Requires-Dist: pyln-proto (>=23.5.2,<24.0.0)
Requires-Dist: pyln-testing (>=0.12.0,<0.13.0)
Requires-Dist: pytest (>=7.0.1,<8.0.0)
Requires-Dist: python-bitcoinlib (>=0.11.2,<0.12.0)
